{
  "title": "something",
  "starred": false,
  "createdAt": 1589983468418,
  "createdBy": {
    "_id": "u101",
    "fullname": "Guest Guestosh",
    "imgUrl": "https://avatarfiles.alphacoders.com/196/196630.jpg"
  },
  "labelOptions": [
    { "id": 1, "color": "green", "name": "" },
    { "id": 2, "color": "yellow", "name": "" },
    { "id": 3, "color": "orange", "name": "" },
    { "id": 4, "color": "red", "name": "" },
    { "id": 5, "color": "purple", "name": "" },
    { "id": 6, "color": "blue", "name": "" }
  ],
  "labels": [
    {
      "id": "l101",
      "title": "Done",
      "color": "#61bd4f"
    }
  ],
  "members": ["johnny"],
  "groupsOrder": ["g101", "g102"],
  "groups": [
    {
      "id": "g101",
      "title": "Group 1",
      "tasksIds": ["c101", "c102"],
      "tasks": [
        {
          "id": "c101",
          "title": "Replace logo"
        },
        {
          "id": "c102",
          "title": "Add Samples"
        }
      ],
      "style": {},
      "editMode": false
    },
    {
      "id": "g102",
      "title": "Group 2",
      "tasksIds": ["c103", "c104"],
      "tasks": [
        {
          "id": "c103",
          "title": "Do that"
        },
        {
          "id": "c104",
          "title": "Help me",
          "status": "in-progress",
          "description": "description",
          "comments": [
            {
              "id": "ZdPnm",
              "initials": "YB",
              "txt": "also @yaronb please CR this",
              "createdAt": 1590999817436.0,
              "byMember": {
                "_id": "u101",
                "initials": "TT",
                "fullname": "Tal Tarablus"
              }
            }
          ],
          "checklists": [
            {
              "id": "YEhmF",
              "title": "Checklist",
              "todos": [
                {
                  "id": "212jX",
                  "title": "To Do 1",
                  "isDone": false
                }
              ]
            }
          ],
          "members": [
            {
              "_id": "u101",
              "username": "Tal",
              "fullname": "Tal Tarablus",
              "initials": "TT"
            }
          ],
          "labelIds": ["l101", "l102"],
          "createdAt": 1590999730348,
          "dueDate": 16156215211,
          "byMember": {
            "_id": "u101",
            "username": "Tal",
            "fullname": "Tal Tarablus",
            "initials": "TT"
          },
          "style": {
            "bgColor": "#26de81"
          }
        }
      ],
      "style": {},
      "editMode": false
    }
  ],
  "activities": [],

  "cmpsOrder": ["status-picker", "member-picker", "date-picker"]
}
